_ckwrap.cpython-312-darwin.so
ckwrap-1.2.3.dist-info/RECORD
ckwrap-1.2.3.dist-info/WHEEL
ckwrap-1.2.3.dist-info/top_level.txt
ckwrap-1.2.3.dist-info/METADATA
ckwrap-1.2.3.dist-info/licenses/LICENSE
ckwrap/_ckwrap.pyx
ckwrap/__init__.py
ckwrap/kmeans_1d_dp.pxd
ckwrap/result.py
ckwrap/ckwrap.py
ckwrap/_ckwrap.cpp
