Metadata-Version: 2.1
Name: ckwrap
Version: 1.2.3
Summary: Python wrapper for Ckmeans.1d.dp, 4.3.5.
Author: djdt
License: GNU LESSER GENERAL PUBLIC LICENSE
Project-URL: Homepage, https://github.com/djdt/ckwrap
License-File: LICENSE
Requires-Dist: numpy
Requires-Dist: Cython
Provides-Extra: test
Requires-Dist: pytest ; extra == 'test'
Requires-Dist: scipy ; extra == 'test'
